anima/__init__.py
anima/__main__.py
anima/core.py
anima/commands/__init__.py
anima/commands/attack.py
anima/commands/combo.py
anima/commands/crit.py
anima/commands/mass.py
anima/commands/powers.py
anima/commands/shuffle.py
anima_utils-0.3.2.dist-info/LICENSE
anima_utils-0.3.2.dist-info/METADATA
anima_utils-0.3.2.dist-info/WHEEL
anima_utils-0.3.2.dist-info/entry_points.txt
anima_utils-0.3.2.dist-info/top_level.txt
anima_utils-0.3.2.dist-info/RECORD
