Metadata-Version: 2.1
Name: anima-utils
Version: 0.3.2
Summary: Utils for assisting players and GMs in the tabletop roleplaying game Anima: Beyond Fantasy
Author-email: Dez <desmeraldoo@gmail.com>
Project-URL: Bug Tracker, https://github.com/desmeraldoo/anima/issues
Project-URL: Homepage, https://github.com/desmeraldoo/anima
Classifier: Programming Language :: Python :: 3
Classifier: License :: OSI Approved :: MIT License
Classifier: Operating System :: OS Independent
Requires-Python: >=3.10
License-File: LICENSE
Requires-Dist: tabulate
